{"rows": [{"amount":"100.000","id":1,"name":"Bag (100g)"},{"amount":"65.000","id":2,"name":"Bag (65g)"},{"amount":"75.000","id":10,"name":"Can (75g)"},{"amount":"330.000","id":11,"name":"Can (330g)"},{"amount":"600.000","id":4,"name":"Bag (600g)"},{"amount":"20.000","id":6,"name":"Bar (20g)"},{"amount":"560.000","id":7,"name":"Can (560g)"},{"amount":"500.000","id":8,"name":"Bottle (500g)"},{"amount":"425.000","id":9,"name":"Can (425g)"},{"amount":"73.000","id":12,"name":"Can (73g)"},{"amount":"275.000","id":13,"name":"Can (275g)"},{"amount":"200.000","id":3,"name":"Bag (200g)"},{"amount":"250.000","id":5,"name":"Bag (250g)"},{"amount":"80.000","id":14,"name":"Can (80g)"},{"amount":"40.000","id":15,"name":"Can (40g)"},{"amount":"17.000","id":16,"name":"Cookie (17g)"}]}